numcodecs_huffman/__init__.py
numcodecs_huffman/py.typed
numcodecs_huffman-0.1.3.dist-info/METADATA
numcodecs_huffman-0.1.3.dist-info/WHEEL
numcodecs_huffman-0.1.3.dist-info/entry_points.txt
numcodecs_huffman-0.1.3.dist-info/licenses/LICENSE
numcodecs_huffman-0.1.3.dist-info/RECORD
