Metadata-Version: 2.4
Name: numcodecs-huffman
Version: 0.1.3
Summary: Huffman codec for the `numcodecs` buffer compression API
License-Expression: MPL-2.0
License-File: LICENSE
Requires-Python: >=3.10
Requires-Dist: dahuffman~=0.4.0
Requires-Dist: leb128~=1.0.8
Requires-Dist: numcodecs<0.17,>=0.13.0
Requires-Dist: numpy~=2.0
Requires-Dist: typing-extensions~=4.6
